noether/Multiplication.py
noether/__init__.py
noether/__main__.py
noether/_tokenizers.py
noether/config.py
noether/display.py
noether/errors.py
noether/gnu.py
noether/helpers.py
noether/catalogue/__init__.py
noether/catalogue/data.py
noether/catalogue/dimensions.py
noether/catalogue/fundamental.py
noether/catalogue/prefixes.py
noether/catalogue/conventional/__init__.py
noether/catalogue/conventional/avourdupois.py
noether/catalogue/conventional/conventional.py
noether/catalogue/conventional/typographic.py
noether/catalogue/historic/__init__.py
noether/catalogue/historic/ancient_greek.units.py
noether/catalogue/historic/ancient_greek_.py
noether/catalogue/historic/mts.units.py
noether/catalogue/historic/mts_.py
noether/catalogue/historic/scientific.py
noether/catalogue/humorous/__init__.py
noether/catalogue/humorous/fictional.py
noether/catalogue/humorous/potrzebie.py
noether/catalogue/humorous/unusual.py
noether/catalogue/info/__init__.py
noether/catalogue/info/comparison.py
noether/catalogue/info/dimension.py
noether/catalogue/info/spectrum.py
noether/catalogue/info/unit_context.py
noether/catalogue/info/unit_value.py
noether/catalogue/scientific/CODATA.py
noether/catalogue/scientific/__init__.py
noether/catalogue/scientific/astronomy.py
noether/catalogue/scientific/cgs.py
noether/catalogue/scientific/constants.py
noether/catalogue/scientific/earth.py
noether/catalogue/scientific/micro.py
noether/catalogue/scientific/misc.py
noether/catalogue/scientific/si.py
noether/core/Catalogue.py
noether/core/Dimension.py
noether/core/Measure.py
noether/core/MeasureInfo.py
noether/core/MeasureRelative.py
noether/core/Prefix.py
noether/core/Unit.py
noether/core/UnitSet.py
noether/core/_DisplayHandler.py
noether/core/__init__.py
noether/core/units/AffineUnit.py
noether/core/units/GeometricUnit.py
noether/core/units/LinearUnit.py
noether/core/units/LogarithmicUnit.py
noether/core/units/PrefixedUnit.py
noether/core/units/__init__.py
noether-1.1.dist-info/LICENSE.txt
noether-1.1.dist-info/METADATA
noether-1.1.dist-info/WHEEL
noether-1.1.dist-info/top_level.txt
noether-1.1.dist-info/RECORD
