Metadata-Version: 2.1
Name: noether
Version: 1.1
Summary: Work with physical measurements and constants
Home-page: https://github.com/yunruse/noether
Author: Mia yun Ruse
Author-email: mia@yunru.se
Keywords: physics unit measure constant measurement uncertainty
Classifier: Programming Language :: Python :: 3
Classifier: Operating System :: OS Independent
Classifier: License :: OSI Approved
Classifier: Topic :: Scientific/Engineering
Classifier: Development Status :: 4 - Beta
Requires-Python: >=3.10
License-File: LICENSE.txt
